optimal_pytorch/__init__.py
optimal_pytorch/coin_betting/__init__.py
optimal_pytorch/coin_betting/torch/__init__.py
optimal_pytorch/coin_betting/torch/cocob.py
optimal_pytorch/coin_betting/torch/onsbet.py
optimal_pytorch/coin_betting/torch/recursive.py
optimal_pytorch/coin_betting/torch/regralizer.py
optimal_pytorch/coin_betting/torch/scinol2.py
optimal_pytorch/coin_betting/torch/sgdol.py
optimal_pytorch/test_functions/__init__.py
optimal_pytorch/test_functions/loss.py
optimal_pytorch-0.1.0.dist-info/LICENSE
optimal_pytorch-0.1.0.dist-info/WHEEL
optimal_pytorch-0.1.0.dist-info/METADATA
optimal_pytorch-0.1.0.dist-info/RECORD
